pathing.py
pathing/__init__.py
pathing-0.1.3.dist-info/LICENCE
pathing-0.1.3.dist-info/METADATA
pathing-0.1.3.dist-info/WHEEL
pathing-0.1.3.dist-info/top_level.txt
pathing-0.1.3.dist-info/RECORD
