Metadata-Version: 2.1
Name: pathing
Version: 0.1.3
Summary: Mapping keys path to value derivation.
Home-page: https://github.com/Exahilosys/pathing
Author: Exahilosys
License: MIT
Platform: UNKNOWN
Classifier: License :: OSI Approved :: MIT License
Classifier: Intended Audience :: Developers
Classifier: Natural Language :: English
Classifier: Operating System :: OS Independent
Classifier: Programming Language :: Python :: 3.6
Classifier: Topic :: Software Development :: Libraries
Classifier: Topic :: Software Development :: Libraries :: Python Modules
Classifier: Topic :: Utilities
